genius_client_sdk/__init__.py
genius_client_sdk/agent.py
genius_client_sdk/auth.py
genius_client_sdk/configuration.py
genius_client_sdk/model.py
genius_client_sdk/pomdp.py
genius_client_sdk/utils.py
genius_client_sdk/converters/__init__.py
genius_client_sdk/converters/bif_to_vfg.py
genius_client_sdk/datamodel/__init__.py
genius_client_sdk/datamodel/api.py
genius_client_sdk/mcp_host/__init__.py
genius_client_sdk/mcp_host/_mcp_adapter.py
genius_client_sdk/mcp_host/_mcp_cli.py
genius_client_sdk/mcp_host/_mcp_env.py
genius_client_sdk/mcp_host/_mcp_server.py
genius_client_sdk/mcp_host/py.typed
genius_client_sdk/mcp_host/tools/__init__.py
genius_client_sdk/mcp_host/tools/act.py
genius_client_sdk/mcp_host/tools/base.py
genius_client_sdk/mcp_host/tools/infer.py
genius_client_sdk/mcp_host/tools/runner.py
genius_client_sdk/mcp_host/utils/validate.py
genius_client_sdk-5.3.0.dist-info/METADATA
genius_client_sdk-5.3.0.dist-info/WHEEL
genius_client_sdk-5.3.0.dist-info/entry_points.txt
genius_client_sdk-5.3.0.dist-info/RECORD
