Metadata-Version: 2.4
Name: genius-client-sdk
Version: 5.3.0
Summary: Client SDK for Genius
Requires-Python: >=3.11
Requires-Dist: inferactively-pymdp==0.0.7.1
Requires-Dist: matplotlib==3.9.2
Requires-Dist: mcp>=1.9.1
Requires-Dist: networkx==3.4.2
Requires-Dist: numpy>1.24.3
Requires-Dist: pyjwt>=2.10.1
Requires-Dist: python-dotenv>=1.0.1
Requires-Dist: pyvfg~=7.1.5
